{
  "testCases": [
    {
      "testCaseId": 1,
      "projectType": "Renewable Retail Electricity",
      "technology": ["=All"],
      "regions": ["Asia (=All)", "Europe (=All)", "Africa (=All)"],
      "minimumAnnualSite": "enter numerical value",
      "minimumTermLength": "enter numeric values 0 to 2147483647",
      "purchaseOptionsAdditionalDetails": ["=All"],
      "valueProvided": ["=All"],
      "timeUrgencyConsiderations": "enter string value or alphanumeric value",
      "additionalComments": "enter string value or alphanumeric value",
      "projectTitle": "enter a alpha numeric value",
      "subTitle": "enter a alpha numeric value",
      "describeOpportunity": "enter a alpha numeric value",
      "aboutTheProvider": "should be auto populated from the company description page",
      "action": "Publish"
    },
    {
      "testCaseId": 2,
      "projectType": "Renewable Retail Electricity",
      "technology": ["Offshore wind"],
      "regions": ["Asia (=All)", "USA & Canada (=All)"],
      "minimumAnnualSite": "enter numerical value",
      "minimumTermLength": "enter numeric values 0 to 2147483647",
      "purchaseOptionsAdditionalDetails": ["Behind the Meter"],
      "valueProvided": ["=All"],
      "timeUrgencyConsiderations": "enter string value or alphanumeric value",
      "additionalComments": "enter string value or alphanumeric value",
      "projectTitle": "enter a alpha numeric value",
      "subTitle": "enter a alphanumeric value",
      "describeOpportunity": "enter a alpha numeric value",
      "aboutTheProvider": "should be auto populated from the company description page",
      "action": "Publish"
    },
    {
      "testCaseId": 3,
      "projectType": "Renewable Retail Electricity",
      "technology": ["Groundmount Solar", "Offshore wind"],
      "regions": ["Asia (=All)", "Europe (=All)", "USA & Canada (=All)"],
      "minimumAnnualSite": "enter numerical value",
      "minimumTermLength": "enter numeric values 0 to 2147483647",
      "purchaseOptionsAdditionalDetails": ["In Front of the Meter"],
      "valueProvided": ["=All"],
      "timeUrgencyConsiderations": "enter string value or alphanumeric value",
      "additionalComments": "enter string value or alphanumeric value",
      "projectTitle": "enter a alpha numeric value",
      "subTitle": "enter a alphanumeric value",
      "describeOpportunity": "enter a alpha numeric value",
      "aboutTheProvider": "should be auto populated from the company description page",
      "action": "Publish"
    },
    {
      "testCaseId": 4,
      "projectType": "Renewable Retail Electricity",
      "technology": ["Offshore wind", "Onshore wind"],
      "regions": ["Africa (=All)", "Oceania (=All)", "Mexico (=All)", "USA & Canada (=All)"],
      "minimumAnnualSite": "enter numerical value",
      "minimumTermLength": "enter numeric values 0 to 2147483647",
      "purchaseOptionsAdditionalDetails": ["=All"],
      "valueProvided": ["Cost Savings", "Other"],
      "timeUrgencyConsiderations": "enter string value or alphanumeric value",
      "additionalComments": "enter string value or alphanumeric value",
      "projectTitle": "enter a alpha numeric value",
      "subTitle": "enter a alphanumeric value",
      "describeOpportunity": "enter a alpha numeric value",
      "aboutTheProvider": "should be auto populated from the company description page",
      "action": "Publish"
    },
    {
      "testCaseId": 5,
      "projectType": "Renewable Retail Electricity",
      "technology": ["Offshore wind"],
      "regions": ["USA & Canada (=All)"],
      "minimumAnnualSite": "enter numerical value",
      "minimumTermLength": "enter numeric values 0 to 2147483647",
      "purchaseOptionsAdditionalDetails": ["In Front of the Meter"],
      "valueProvided": ["=All"],
      "timeUrgencyConsiderations": "enter string value or alphanumeric value",
      "additionalComments": "enter string value or alphanumeric value",
      "projectTitle": "enter a alpha numeric value",
      "subTitle": "enter a alphanumeric value",
      "describeOpportunity": "enter a alpha numeric value",
      "aboutTheProvider": "should be auto populated from the company description page",
      "action": "Publish"
    },
    {
      "testCaseId": 6,
      "projectType": "Renewable Retail Electricity",
      "technology": ["Onshore wind"],
      "regions": ["Asia (=All)"],
      "minimumAnnualSite": "enter numerical value",
      "minimumTermLength": "enter numeric values 0 to 2147483647",
      "purchaseOptionsAdditionalDetails": ["Behind the Meter"],
      "valueProvided": ["=All"],
      "timeUrgencyConsiderations": "enter string value or alphanumeric value",
      "additionalComments": "enter string value or alphanumeric value",
      "projectTitle": "enter a string with full length of 100 character string",
      "subTitle": "enter a alphanumeric value",
      "describeOpportunity": "enter a alpha numeric value",
      "aboutTheProvider": "should be auto populated from the company description page",
      "action": "Publish"
    },
    {
      "testCaseId": 7,
      "projectType": "Renewable Retail Electricity",
      "technology": ["Offshore wind"],
      "regions": ["Asia (=All)"],
      "minimumAnnualSite": "enter numerical value",
      "minimumTermLength": "enter numeric values 0 to 2147483647",
      "purchaseOptionsAdditionalDetails": ["=All"],
      "valueProvided": ["=All"],
      "timeUrgencyConsiderations": "enter string value or alphanumeric value",
      "additionalComments": "enter string value or alphanumeric value",
      "projectTitle": "enter a alpha numeric value",
      "subTitle": "enter a alphanumeric value",
      "describeOpportunity": "enter a alpha numeric value",
      "aboutTheProvider": "should be auto populated from the company description page",
      "action": "Publish"
    },
    {
      "testCaseId": 8,
      "projectType": "Renewable Retail Electricity",
      "technology": ["Groundmount Solar"],
      "regions": ["Africa (=All)", "USA & Canada (=All)"],
      "minimumAnnualSite": "enter numerical value",
      "minimumTermLength": "enter numeric values 0 to 2147483647",
      "purchaseOptionsAdditionalDetails": ["Behind the Meter"],
      "valueProvided": ["Cost Savings"],
      "timeUrgencyConsiderations": "enter string value or alphanumeric value",
      "additionalComments": "enter string value or alphanumeric value",
      "projectTitle": "enter a alpha numeric value",
      "subTitle": "enter a alphanumeric value",
      "describeOpportunity": "enter a alpha numeric value",
      "aboutTheProvider": "should be auto populated from the company description page",
      "action": "Publish"
    },
    {
      "testCaseId": 9,
      "projectType": "Renewable Retail Electricity",
      "technology": ["Groundmount Solar"],
      "regions": ["Asia (=All)", "USA & Canada (=All)"],
      "minimumAnnualSite": "178",
      "minimumTermLength": "enter numeric values 0 to 2147483647",
      "purchaseOptionsAdditionalDetails": ["Behind the Meter"],
      "valueProvided": ["Renewable Attributes"],
      "projectTitle": "enter a alpha numeric value",
      "subTitle": "enter a alphanumeric value",
      "describeOpportunity": "enter a alpha numeric value",
      "aboutTheProvider": "should be auto populated from the company description page",
      "action": "Publish"
    },
    {
      "testCaseId": 10,
      "projectType": "Renewable Retail Electricity",
      "technology": ["Offshore wind"],
      "regions": ["Africa (=All)", "Asia (=All)", "Europe (=All)", "Mexico & Central America (=All)", "Oceania (=All)", "South America (=All)", "USA & Canada (=All)"],
      "minimumAnnualSite": "enter numerical value",
      "minimumTermLength": "enter numeric values 0 to 2147483647",
      "purchaseOptionsAdditionalDetails": ["Behind the Meter"],
      "valueProvided": ["Other"],
      "additionalComments": "enter string value or alphanumeric value",
      "projectTitle": "enter a alpha numeric value",
      "subTitle": "enter a alphanumeric value",
      "describeOpportunity": "enter a alpha numeric value",
      "aboutTheProvider": "should be auto populated from the company description page",
      "action": "Publish"
    },
    {
      "testCaseId": 11,
      "projectType": "Renewable Retail Electricity",
      "technology": ["Offshore wind", "Groundmount Solar"],
      "regions": ["Asia (=All)", "USA & Canada (=All)"],
      "minimumAnnualSite": "enter numerical value",
      "minimumTermLength": "enter numeric values 0 to 2147483647",
      "purchaseOptionsAdditionalDetails": ["In Front of the Meter"],
      "valueProvided": ["=All"],
      "timeUrgencyConsiderations": "enter string value or alphanumeric value",
      "additionalComments": "enter string value or alphanumeric value",
      "projectTitle": "enter a alpha numeric value",
      "subTitle": "enter a alphanumeric value with full length of 200 characters",
      "describeOpportunity": "enter a alpha numeric value with maximum of 4000 character string",
      "aboutTheProvider": "should be auto populated from the company description page",
      "action": "Publish"
    },
    {
      "testCaseId": 12,
      "projectType": "Renewable Retail Electricity",
      "technology": ["Offshore wind", "Onshore wind"],
      "regions": ["USA & Canada (=All)"],
      "minimumAnnualSite": "enter numerical value",
      "minimumTermLength": "enter numeric values 0 to 2147483647",
      "purchaseOptionsAdditionalDetails": ["Behind the Meter"],
      "valueProvided": ["Other"],
      "timeUrgencyConsiderations": "enter string value or alphanumeric value",
      "additionalComments": "enter string value or alphanumeric value",
      "projectTitle": "enter a alpha numeric value",
      "subTitle": "enter a alphanumeric value",
      "describeOpportunity": "enter a alpha numeric value",
      "aboutTheProvider": "should be auto populated from the company description page",
      "action": "Publish"
    },
    {
      "testCaseId": 13,
      "projectType": "Renewable Retail Electricity",
      "technology": ["Groundmount Solar", "Offshore wind", "Onshore wind"],
      "regions": ["Mexico & Central America (=All)"],
      "minimumAnnualSite": "enter numerical value",
      "minimumTermLength": "enter numeric values 0 to 2147483647",
      "purchaseOptionsAdditionalDetails": ["Behind the Meter"],
      "valueProvided": ["Cost Savings"],
      "timeUrgencyConsiderations": "enter string value or alphanumeric value",
      "additionalComments": "enter string value or alphanumeric value",
      "projectTitle": "enter a alpha numeric value",
      "subTitle": "enter a alphanumeric value",
      "describeOpportunity": "enter a alpha numeric value",
      "aboutTheProvider": "should be auto populated from the company description page",
      "action": "Publish"
    },
    {
      "testCaseId": 14,
      "projectType": "Renewable Retail Electricity",
      "technology": ["Offshore wind", "Onshore wind"],
      "regions": ["Africa (=All)", "Asia (=All)", "Europe (=All)", "Mexico & Central America (=All)", "Oceania (=All)", "South America (=All)", "USA & Canada (=All)"],
      "minimumAnnualSite": "enter numerical value",
      "minimumTermLength": "enter numeric values 0 to 2147483647",
      "purchaseOptionsAdditionalDetails": ["=All"],
      "valueProvided": ["=All"],
      "timeUrgencyConsiderations": "enter string value or alphanumeric value",
      "additionalComments": "enter string value or alphanumeric value",
      "projectTitle": "enter a alpha numeric value",
      "subTitle": "enter a alphanumeric value",
      "describeOpportunity": "enter a alpha numeric value",
      "aboutTheProvider": "should be auto populated from the company description page",
      "action": "Publish"
    },
    {
      "testCaseId": 15,
      "projectType": "Renewable Retail Electricity",
      "technology": ["Onshore wind"],
      "regions": ["Asia (=All)", "USA & Canada (=All)"],
      "minimumAnnualSite": "enter numerical value",
      "minimumTermLength": "enter numeric values 0 to 2147483647",
      "purchaseOptionsAdditionalDetails": ["Behind the Meter"],
      "valueProvided": ["=All"],
      "timeUrgencyConsiderations": "enter string value or alphanumeric value",
      "additionalComments": "enter string value or alphanumeric value",
      "projectTitle": "enter a alpha numeric value",
      "subTitle": "enter a alphanumeric value",
      "describeOpportunity": "enter a alpha numeric value",
      "aboutTheProvider": "should be auto populated from the company description page",
      "action": "Publish"
    },
    {
      "testCaseId": 16,
      "projectType": "Renewable Retail Electricity",
      "technology": ["Offshore wind", "Onshore wind"],
      "regions": ["Asia (=All)", "USA & Canada (=All)"],
      "minimumAnnualSite": "enter numerical value",
      "minimumTermLength": "enter numeric values 0 to 2147483647",
      "purchaseOptionsAdditionalDetails": ["In Front of the Meter"],
      "valueProvided": ["=All"],
      "timeUrgencyConsiderations": "enter string value or alphanumeric value",
      "additionalComments": "enter string value or alphanumeric value",
      "projectTitle": "enter a alpha numeric value",
      "subTitle": "enter a alphanumeric value",
      "describeOpportunity": "enter a alpha numeric value",
      "aboutTheProvider": "should be auto populated from the company description page",
      "action": "Publish"
    },
    {
      "testCaseId": 17,
      "projectType": "Renewable Retail Electricity",
      "technology": ["Groundmount Solar", "Offshore wind", "Onshore wind"],
      "regions": ["Asia (=All)", "USA & Canada (=All)"],
      "minimumAnnualSite": "enter numerical value",
      "minimumTermLength": "enter numeric values 0 to 2147483647",
      "purchaseOptionsAdditionalDetails": ["Behind the Meter"],
      "valueProvided": ["=All"],
      "timeUrgencyConsiderations": "enter string value or alphanumeric value",
      "additionalComments": "enter string value or alphanumeric value",
      "projectTitle": "enter a alpha numeric value",
      "subTitle": "enter a alphanumeric value",
      "describeOpportunity": "enter a alpha numeric value",
      "aboutTheProvider": "should be auto populated from the company description page",
      "action": "Publish"
    },
    {
      "testCaseId": 18,
      "projectType": "Renewable Retail Electricity",
      "technology": ["Offshore wind", "Onshore wind"],
      "regions": ["Asia (=All)", "USA & Canada (=All)"],
      "minimumAnnualSite": "enter numerical value",
      "minimumTermLength": "enter numeric values 0 to 2147483647",
      "purchaseOptionsAdditionalDetails": ["Behind the Meter"],
      "valueProvided": ["Renewable Attributes"],
      "timeUrgencyConsiderations": "enter string value or alphanumeric value",
      "additionalComments": "enter string value or alphanumeric value",
      "projectTitle": "enter a alpha numeric value",
      "subTitle": "enter a alphanumeric value",
      "describeOpportunity": "enter a alpha numeric value",
      "aboutTheProvider": "should be auto populated from the company description page",
      "action": "Publish"
    },
    {
      "testCaseId": 19,
      "projectType": "Renewable Retail Electricity",
      "technology": ["Onshore wind"],
      "regions": ["Africa (=All)", "Asia (=All)", "USA & Canada (=All)"],
      "minimumAnnualSite": "enter numerical value",
      "minimumTermLength": "enter numeric values 0 to 2147483647",
      "purchaseOptionsAdditionalDetails": ["Behind the Meter"],
      "valueProvided": ["=All"],
      "timeUrgencyConsiderations": "enter string value or alphanumeric value",
      "additionalComments": "enter string value or alphanumeric value",
      "projectTitle": "enter a alpha numeric value",
      "subTitle": "enter a alphanumeric value",
      "describeOpportunity": "enter a alpha numeric value",
      "aboutTheProvider": "should be auto populated from the company description page",
      "action": "Publish"
    },
    {
      "testCaseId": 20,
      "projectType": "Renewable Retail Electricity",
      "technology": ["Groundmount Solar", "Offshore wind", "Onshore wind"],
      "regions": ["Asia (=All)", "USA & Canada (=All)"],
      "minimumAnnualSite": "enter numerical value",
      "minimumTermLength": "enter numeric values 0 to 2147483647",
      "purchaseOptionsAdditionalDetails": ["Behind the Meter"],
      "valueProvided": ["Cost Savings"],
      "timeUrgencyConsiderations": "enter string value or alphanumeric value",
      "additionalComments": "enter string value or alphanumeric value",
      "projectTitle": "enter a alpha numeric value",
      "subTitle": "enter a alphanumeric value",
      "describeOpportunity": "enter a alpha numeric value",
      "aboutTheProvider": "should be auto populated from the company description page",
      "action": "Publish"
    },
    {
      "testCaseId": 21,
      "projectType": "Renewable Retail Electricity",
      "technology": ["Groundmount Solar"],
      "regions": ["South America (=All)"],
      "minimumAnnualSite": "enter numerical value",
      "minimumTermLength": "enter numeric values 0 to 2147483647",
      "purchaseOptionsAdditionalDetails": ["Behind the Meter"],
      "valueProvided": ["Cost Savings"],
      "timeUrgencyConsiderations": "enter string value or alphanumeric value",
      "additionalComments": "enter string value or alphanumeric value",
      "projectTitle": "enter a alpha numeric value",
      "subTitle": "enter a alphanumeric value",
      "describeOpportunity": "enter a alpha numeric value",
      "aboutTheProvider": "should be auto populated from the company description page",
      "action": "Publish"
    },
    {
      "testCaseId": 22,
      "projectType": "Renewable Retail Electricity",
      "technology": ["Groundmount Solar", "Offshore wind", "Onshore wind"],
      "regions": ["Oceania (=All)"],
      "minimumAnnualSite": "enter numerical value",
      "minimumTermLength": "enter numeric values 0 to 2147483647",
      "purchaseOptionsAdditionalDetails": ["Behind the Meter"],
      "valueProvided": ["Cost Savings"],
      "timeUrgencyConsiderations": "enter string value or alphanumeric value",
      "additionalComments": "enter string value or alphanumeric value",
      "projectTitle": "enter a alpha numeric value",
      "subTitle": "enter a alphanumeric value",
      "describeOpportunity": "enter a alpha numeric value",
      "aboutTheProvider": "should be auto populated from the company description page",
      "action": "Publish"
    },
    {
      "testCaseId": 23,
      "projectType": "Renewable Retail Electricity",
      "technology": ["Groundmount Solar", "Offshore wind", "Onshore wind"],
      "regions": ["Mexico & Central America (=All)"],
      "minimumAnnualSite": "enter numerical value",
      "minimumTermLength": "enter numeric values 0 to 2147483647",
      "purchaseOptionsAdditionalDetails": ["In front of the Meter"],
      "valueProvided": ["Cost Savings", "Other"],
      "timeUrgencyConsiderations": "enter string value or alphanumeric value",
      "additionalComments": "enter string value or alphanumeric value",
      "projectTitle": "enter a alpha numeric value",
      "subTitle": "enter a alphanumeric value",
      "describeOpportunity": "enter a alpha numeric value",
      "aboutTheProvider": "should be auto populated from the company description page",
      "action": "Publish"
    }
  ]
}
